mem0/__init__.py
mem0/exceptions.py
mem0/client/__init__.py
mem0/client/main.py
mem0/client/project.py
mem0/client/utils.py
mem0/configs/__init__.py
mem0/configs/base.py
mem0/configs/enums.py
mem0/configs/prompts.py
mem0/configs/embeddings/__init__.py
mem0/configs/embeddings/base.py
mem0/configs/llms/__init__.py
mem0/configs/llms/anthropic.py
mem0/configs/llms/aws_bedrock.py
mem0/configs/llms/azure.py
mem0/configs/llms/base.py
mem0/configs/llms/deepseek.py
mem0/configs/llms/lmstudio.py
mem0/configs/llms/ollama.py
mem0/configs/llms/openai.py
mem0/configs/llms/vllm.py
mem0/configs/vector_stores/__init__.py
mem0/configs/vector_stores/azure_ai_search.py
mem0/configs/vector_stores/baidu.py
mem0/configs/vector_stores/chroma.py
mem0/configs/vector_stores/databricks.py
mem0/configs/vector_stores/elasticsearch.py
mem0/configs/vector_stores/faiss.py
mem0/configs/vector_stores/langchain.py
mem0/configs/vector_stores/milvus.py
mem0/configs/vector_stores/mongodb.py
mem0/configs/vector_stores/neptune.py
mem0/configs/vector_stores/opensearch.py
mem0/configs/vector_stores/pgvector.py
mem0/configs/vector_stores/pinecone.py
mem0/configs/vector_stores/qdrant.py
mem0/configs/vector_stores/redis.py
mem0/configs/vector_stores/s3_vectors.py
mem0/configs/vector_stores/supabase.py
mem0/configs/vector_stores/upstash_vector.py
mem0/configs/vector_stores/valkey.py
mem0/configs/vector_stores/vertex_ai_vector_search.py
mem0/configs/vector_stores/weaviate.py
mem0/embeddings/__init__.py
mem0/embeddings/aws_bedrock.py
mem0/embeddings/azure_openai.py
mem0/embeddings/base.py
mem0/embeddings/configs.py
mem0/embeddings/gemini.py
mem0/embeddings/huggingface.py
mem0/embeddings/langchain.py
mem0/embeddings/lmstudio.py
mem0/embeddings/mock.py
mem0/embeddings/ollama.py
mem0/embeddings/openai.py
mem0/embeddings/together.py
mem0/embeddings/vertexai.py
mem0/graphs/__init__.py
mem0/graphs/configs.py
mem0/graphs/tools.py
mem0/graphs/utils.py
mem0/graphs/neptune/__init__.py
mem0/graphs/neptune/base.py
smem_mention-0.0.9.dist-info/METADATA
smem_mention-0.0.9.dist-info/WHEEL
smem_mention-0.0.9.dist-info/licenses/LICENSE
smem_mention-0.0.9.dist-info/RECORD
